utils/__init__.py
utils/check_python.py
utils/format_markdown.py
utils/format_yaml.py
utils/lint.py
utils/validate_docker.py
utils/verify_build.py
utils/verify_docker.py
utils/verify_gpu.py
stockula/__init__.py
stockula/__main__.py
stockula/cli.py
stockula/cli_manager.py
stockula/container.py
stockula/display.py
stockula/interfaces.py
stockula/main.py
stockula/manager.py
stockula/allocation/__init__.py
stockula/allocation/allocator.py
stockula/allocation/backtest_allocator.py
stockula/allocation/base_allocator.py
stockula/allocation/manager.py
stockula/backtesting/__init__.py
stockula/backtesting/indicators.py
stockula/backtesting/manager.py
stockula/backtesting/metrics.py
stockula/backtesting/registry.py
stockula/backtesting/runner.py
stockula/backtesting/strategies.py
stockula/config/__init__.py
stockula/config/exceptions.py
stockula/config/models.py
stockula/config/settings.py
stockula/data/__init__.py
stockula/data/fetcher.py
stockula/data/manager.py
stockula/data/registry.py
stockula/data/repository.py
stockula/data/strategy_repository.py
stockula/database/__init__.py
stockula/database/manager.py
stockula/database/models.py
stockula/domain/__init__.py
stockula/domain/asset.py
stockula/domain/category.py
stockula/domain/factory.py
stockula/domain/portfolio.py
stockula/domain/ticker.py
stockula/domain/ticker_wrapper.py
stockula/forecasting/__init__.py
stockula/forecasting/factory.py
stockula/forecasting/manager.py
stockula/forecasting/backends/__init__.py
stockula/forecasting/backends/autogluon.py
stockula/forecasting/backends/base.py
stockula/forecasting/backends/chronos.py
stockula/forecasting/backends/simple.py
stockula/technical_analysis/__init__.py
stockula/technical_analysis/indicators.py
stockula/technical_analysis/manager.py
stockula/utils/__init__.py
stockula/utils/logging_manager.py
stockula-0.16.0.dist-info/METADATA
stockula-0.16.0.dist-info/WHEEL
stockula-0.16.0.dist-info/entry_points.txt
stockula-0.16.0.dist-info/RECORD
