Metadata-Version: 2.4
Name: stockula
Version: 0.16.0
Author-email: Mitchell Murphy <mitch.murphy@gmail.com>
License: MIT
Requires-Python: >=3.11
Requires-Dist: alembic==1.16.4
Requires-Dist: backtesting>=0.6.4
Requires-Dist: dependency-injector>=4.48.1
Requires-Dist: finta>=1.3
Requires-Dist: numpy>=2.1.0
Requires-Dist: pandas>=2.3.1
Requires-Dist: pydantic-settings>=2.10.1
Requires-Dist: pyyaml>=6.0.2
Requires-Dist: rich>=14.1.0
Requires-Dist: scikit-learn>=1.5.0
Requires-Dist: sqlalchemy>=2.0.41
Requires-Dist: sqlmodel>=0.0.22
Requires-Dist: typer>=0.16.0
Requires-Dist: yfinance>=0.2.65
Provides-Extra: dev
Requires-Dist: pytest>=8.4.1; extra == 'dev'
Requires-Dist: ruff>=0.12.5; extra == 'dev'
Provides-Extra: forecasting
Requires-Dist: autogluon-timeseries>=1.2.0; (python_version < '3.13') and extra == 'forecasting'
Provides-Extra: gpu
Requires-Dist: lightgbm>=4.0.0; extra == 'gpu'
Requires-Dist: torch>=2.0.0; extra == 'gpu'
Requires-Dist: xgboost>=2.0.0; extra == 'gpu'
